fake_progress_bars/__init__.py
fake_progress_bars-1.0.0.dist-info/METADATA
fake_progress_bars-1.0.0.dist-info/WHEEL
fake_progress_bars-1.0.0.dist-info/licenses/LICENSE
fake_progress_bars-1.0.0.dist-info/RECORD
