Metadata-Version: 2.1
Name: fake_progress_bars
Version: 1.0.0
Summary: A package for creating customizable, fake progress bars.
Project-URL: Homepage, https://github.com/RemyIsCool/fake_progress_bars
Project-URL: Issues, https://github.com/RemyIsCool/fake_progress_bars/issues
Author-email: Remy <remyisahuman@gmail.com>
License-File: LICENSE
Classifier: License :: OSI Approved :: MIT License
Classifier: Operating System :: OS Independent
Classifier: Programming Language :: Python :: 3
Requires-Python: >=3.8
